hwaddress/__init__.py
hwaddress/core.py
hwaddress-1.0.0.dist-info/LICENSE
hwaddress-1.0.0.dist-info/METADATA
hwaddress-1.0.0.dist-info/WHEEL
hwaddress-1.0.0.dist-info/top_level.txt
hwaddress-1.0.0.dist-info/RECORD
