Metadata-Version: 2.1
Name: hwaddress
Version: 1.0.0
Summary: Lightweight EUI-48/64 based hardware (MAC) address library.
Author-email: Eric Geldmacher <egeldmacher@wustl.edu>
Project-URL: Homepage, https://codeberg.org/nbcli/hwaddress
Project-URL: Bug Tracker, https://codeberg.org/nbcli/hwaddress/issues
Classifier: Programming Language :: Python :: 3
Classifier: License :: OSI Approved :: MIT License
Classifier: Operating System :: OS Independent
Requires-Python: >=3.7
License-File: LICENSE
